navani/__init__.py
navani/echem.py
navani-0.1.13.dist-info/licenses/LICENSE
navani-0.1.13.dist-info/METADATA
navani-0.1.13.dist-info/WHEEL
navani-0.1.13.dist-info/top_level.txt
navani-0.1.13.dist-info/RECORD
