Metadata-Version: 2.4
Name: navani
Version: 0.1.13
Summary: Package for processing and plotting echem data from cyclers
Author-email: Ben Smith <ben.ed.smith2@gmail.com>
License: MIT
Project-URL: Homepage, https://github.com/be-smith/navani
Project-URL: Issues, https://github.com/be-smith/navani/issues
Project-URL: Documentation, https://be-smith.github.io/navani/
Requires-Python: >=3.10
License-File: LICENSE
Requires-Dist: numpy<2,~=1.26
Requires-Dist: pandas<3,~=2.2
Requires-Dist: scipy<2,~=1.15
Requires-Dist: datalab-org-galvani>=0.5.0
Requires-Dist: matplotlib<4,~=3.10
Requires-Dist: openpyxl<4,~=3.1
Requires-Dist: NewareNDA>=2024.8.1
Requires-Dist: requests<3,~=2.32
Dynamic: license-file
